MANIFEST.in
README.md
pyproject.toml
setup.py
src/taimos.cdk_construct_hosting.egg-info/PKG-INFO
src/taimos.cdk_construct_hosting.egg-info/SOURCES.txt
src/taimos.cdk_construct_hosting.egg-info/dependency_links.txt
src/taimos.cdk_construct_hosting.egg-info/requires.txt
src/taimos.cdk_construct_hosting.egg-info/top_level.txt
src/taimos/cdk_construct_hosting/__init__.py
src/taimos/cdk_construct_hosting/py.typed
src/taimos/cdk_construct_hosting/_jsii/__init__.py
src/taimos/cdk_construct_hosting/_jsii/cdk-construct-hosting@1.0.0.jsii.tgz