Metadata-Version: 2.1
Name: taimos.cdk-construct-hosting
Version: 1.0.0
Summary: An AWS CDK Construct that provides website hosting
Home-page: https://github.com/taimos/cdk-construct-sample
Author: Thorsten Hoeger<thorsten.hoeger@taimos.de>
License: Apache-2.0
Project-URL: Source, https://github.com/taimos/cdk-construct-sample
Platform: UNKNOWN
Classifier: Intended Audience :: Developers
Classifier: Operating System :: OS Independent
Classifier: Programming Language :: JavaScript
Classifier: Programming Language :: Python :: 3 :: Only
Classifier: Programming Language :: Python :: 3.6
Classifier: Programming Language :: Python :: 3.7
Classifier: Programming Language :: Python :: 3.8
Classifier: Typing :: Typed
Classifier: License :: OSI Approved
Requires-Python: >=3.6
